emllm/__init__.py
emllm/api.py
emllm/cli.py
emllm/core.py
emllm/validator.py
emllm-0.1.10.dist-info/LICENSE
emllm-0.1.10.dist-info/METADATA
emllm-0.1.10.dist-info/WHEEL
emllm-0.1.10.dist-info/entry_points.txt
emllm-0.1.10.dist-info/RECORD
