Metadata-Version: 2.3
Name: emllm
Version: 0.1.10
Summary: Large Language Model Email Message registry and interpreter
License: Apache-2.0
Author: Tom Sapletta
Author-email: info@softreck.dev
Requires-Python: >=3.8.1,<4.0
Classifier: Development Status :: 3 - Alpha
Classifier: Intended Audience :: Developers
Classifier: License :: OSI Approved :: Apache Software License
Classifier: Programming Language :: Python :: 3
Classifier: Programming Language :: Python :: 3.9
Classifier: Programming Language :: Python :: 3.10
Classifier: Programming Language :: Python :: 3.11
Classifier: Programming Language :: Python :: 3.12
Classifier: Programming Language :: Python :: 3.13
Classifier: Programming Language :: Python :: 3.8
Requires-Dist: fastapi (>=0.104.1,<0.105.0)
Requires-Dist: pydantic (>=2.4.2,<3.0.0)
Requires-Dist: uvicorn (>=0.24.0,<0.25.0)
Project-URL: Bug Tracker, https://github.com/emllm/eml/issues
Project-URL: Homepage, https://github.com/emllm/eml
